wedata_mlflow_header_plugin/__init__.py
wedata_mlflow_header_plugin/plugin.py
wedata_mlflow_header_plugin-0.1.2.dist-info/WHEEL
wedata_mlflow_header_plugin-0.1.2.dist-info/entry_points.txt
wedata_mlflow_header_plugin-0.1.2.dist-info/METADATA
wedata_mlflow_header_plugin-0.1.2.dist-info/RECORD
