Metadata-Version: 2.3
Name: wedata-mlflow-header-plugin
Version: 0.1.2
Summary: MLflow request header provider plugin that adds Wedata custom headers
Author: Centon Huang
Author-email: Centon Huang <centonhuang@tencent.com>
Classifier: Development Status :: 3 - Alpha
Classifier: Intended Audience :: Developers
Classifier: Programming Language :: Python :: 3
Classifier: Programming Language :: Python :: 3.8
Classifier: Programming Language :: Python :: 3.9
Classifier: Programming Language :: Python :: 3.10
Classifier: Programming Language :: Python :: 3.11
Requires-Dist: mlflow>=2.0.0
Requires-Python: >=3.8
